MANIFEST.in
README.md
requirements.txt
setup.cfg
setup.py
test_requirements.txt
src/neuroglancer_annotation_ui/__init__.py
src/neuroglancer_annotation_ui/annotation.py
src/neuroglancer_annotation_ui/base.py
src/neuroglancer_annotation_ui/utils.py
src/neuroglancer_annotation_ui.egg-info/PKG-INFO
src/neuroglancer_annotation_ui.egg-info/SOURCES.txt
src/neuroglancer_annotation_ui.egg-info/dependency_links.txt
src/neuroglancer_annotation_ui.egg-info/requires.txt
src/neuroglancer_annotation_ui.egg-info/top_level.txt
src/neuroglancer_annotation_ui/statebuilder/__init__.py
src/neuroglancer_annotation_ui/statebuilder/statebuilder.py
src/neuroglancer_annotation_ui/statebuilder/utils.py