Metadata-Version: 1.0
Name: neuroglancer-annotation-ui
Version: 1.0.0
Summary: Neuroglancer python annotation UI framework.
Home-page: https://github.com/seung-lab/neuroglancer_annotation_ui
Author: Derrick Brittain, Casey Schneider-Mizell, Forrest Collman
Author-email: caseysm@gmail.com
License: UNKNOWN
Platform: UNKNOWN
